robustbench/__init__.py
robustbench/data.py
robustbench/eval.py
robustbench/loaders.py
robustbench/utils.py
robustbench/zenodo_download.py
robustbench/leaderboard/__init__.py
robustbench/leaderboard/template.py
robustbench/model_zoo/__init__.py
robustbench/model_zoo/cifar10.py
robustbench/model_zoo/cifar100.py
robustbench/model_zoo/enums.py
robustbench/model_zoo/imagenet.py
robustbench/model_zoo/models.py
robustbench/model_zoo/architectures/CARD_resnet.py
robustbench/model_zoo/architectures/__init__.py
robustbench/model_zoo/architectures/boosting_wide_resnet.py
robustbench/model_zoo/architectures/dm_wide_resnet.py
robustbench/model_zoo/architectures/paf_wide_resnet.py
robustbench/model_zoo/architectures/resnest.py
robustbench/model_zoo/architectures/resnet.py
robustbench/model_zoo/architectures/resnext.py
robustbench/model_zoo/architectures/robust_wide_resnet.py
robustbench/model_zoo/architectures/utils_architectures.py
robustbench/model_zoo/architectures/wide_resnet.py
torchattacks/__init__.py
torchattacks/attack.py
torchattacks/attacks/__init__.py
torchattacks/attacks/_differential_evolution.py
torchattacks/attacks/apgd.py
torchattacks/attacks/apgdt.py
torchattacks/attacks/autoattack.py
torchattacks/attacks/bim.py
torchattacks/attacks/cw.py
torchattacks/attacks/deepfool.py
torchattacks/attacks/difgsm.py
torchattacks/attacks/eaden.py
torchattacks/attacks/eadl1.py
torchattacks/attacks/eotpgd.py
torchattacks/attacks/fab.py
torchattacks/attacks/ffgsm.py
torchattacks/attacks/fgsm.py
torchattacks/attacks/gn.py
torchattacks/attacks/jitter.py
torchattacks/attacks/jsma.py
torchattacks/attacks/mifgsm.py
torchattacks/attacks/nifgsm.py
torchattacks/attacks/onepixel.py
torchattacks/attacks/pgd.py
torchattacks/attacks/pgdl2.py
torchattacks/attacks/pgdrs.py
torchattacks/attacks/pgdrsl2.py
torchattacks/attacks/pifgsm.py
torchattacks/attacks/pifgsmpp.py
torchattacks/attacks/pixle.py
torchattacks/attacks/rfgsm.py
torchattacks/attacks/sinifgsm.py
torchattacks/attacks/sparsefool.py
torchattacks-3.5.1.dist-info/LICENSE
torchattacks-3.5.1.dist-info/METADATA
torchattacks-3.5.1.dist-info/WHEEL
torchattacks-3.5.1.dist-info/top_level.txt
torchattacks-3.5.1.dist-info/RECORD
